{
	"basics": {
		"name": "Gourav Yadav",
		"label": "Student",
		"picture": "https://avatars.githubusercontent.com/u/79785892?s=400&u=24b070d98a70ab0690792f8d328e06524bcfd8e4&v=4",
		"email": "2020kucp1007@iiitkota.ac.in",
		"phone": "8889781050",
		"website": "https://linktr.ee/ll.gourav.ll_",
		"summary": "I'm a student of Indian Institute of Information Technology Kota (India), pursuing my B.tech in Computer Science & Engineering. I have enthusiasm in Web Development & UI/UX Designing.",
		"location": {
			"address": "Ward No. 6, Satwas, Distt. Dewas, M.P. ",
			"postalCode": "455459",
			"city": "Satwas",
			"countryCode": "India",
			"region": "Madhya Pradesh"
		},
		"profiles": [
			{
				"network": "Github",
				"username": "gourav-yadavv",
				"url": "https://github.com/gourav-yadavv"
			},
			{
				"network": "linkedin",
				"username": "gourav-yadav",
				"url": "https://www.linkedin.com/in/gourav-yadav-2bba9b1bb"
			},
			{
				"network": "Instagram",
				"username": "ll.gourav.ll_",
				"url": "https://www.instagram.com/ll.gourav.ll_/"
			}
		]
	},

	"education": [{
		"institution": "Indian Institute of Information Technology,Kota",
		"area": "Engineering",
		"studyType": "Bachelor (hons)",
		"startDate": "2020-12-02",
		"gpa": "8.77",
		"courses": [
			"Computer Science & Engineering"
		]
	}],
	"skills": [{
		"level": "Master",
		"keywords": ["HTML", "CSS", "Javascript","PHP","MySQL", "UI/UX Design|Figma", "C"]
	}],
	
     "interests": [{
		"name": "Sports",
		"keywords": ["Cricket", "Badminton"]
	}],
	"references": []
}
